lms_bysenser/__init__.py
lms_bysenser/admin.py
lms_bysenser/apps.py
lms_bysenser/models.py
lms_bysenser/services.py
lms_bysenser/tests.py
lms_bysenser/urls.py
lms_bysenser/utils.py
lms_bysenser/views.py
lms_bysenser/migrations/__init__.py
lms_bysenser/static/lms_bysenser/css/lib/element-plus.css
lms_bysenser/static/lms_bysenser/js/lib/element/dayjs.min.js
lms_bysenser/static/lms_bysenser/js/lib/element/element-plus.min.js
lms_bysenser/static/lms_bysenser/js/lib/element/zh-cn.js
lms_bysenser/static/lms_bysenser/js/lib/vue/vue.global.prod.js
lms_bysenser/templates/common.html
lms_bysenser/templates/lms_bysenser/console.html
lms_bysenser-0.1.0.dist-info/licenses/LICENSE
lms_bysenser-0.1.0.dist-info/METADATA
lms_bysenser-0.1.0.dist-info/WHEEL
lms_bysenser-0.1.0.dist-info/top_level.txt
lms_bysenser-0.1.0.dist-info/RECORD
